setup.py
surn3k/__init__.py
surn3k/srun3k.py
surn3k_login.egg-info/PKG-INFO
surn3k_login.egg-info/SOURCES.txt
surn3k_login.egg-info/dependency_links.txt
surn3k_login.egg-info/entry_points.txt
surn3k_login.egg-info/requires.txt
surn3k_login.egg-info/top_level.txt