Metadata-Version: 1.0
Name: surn3k-login
Version: 0.0.3
Summary: 河南工业大学校园网登陆器
Home-page: http://blog.fyved24.de
Author: zh
Author-email: fyved24@163.com
License: UNKNOWN
Platform: UNKNOWN
